formtools/__init__.py
formtools/apps.py
formtools/models.py
formtools/preview.py
formtools/utils.py
formtools/locale/af/LC_MESSAGES/django.mo
formtools/locale/af/LC_MESSAGES/django.po
formtools/locale/ar/LC_MESSAGES/django.mo
formtools/locale/ar/LC_MESSAGES/django.po
formtools/locale/ast/LC_MESSAGES/django.mo
formtools/locale/ast/LC_MESSAGES/django.po
formtools/locale/az/LC_MESSAGES/django.mo
formtools/locale/az/LC_MESSAGES/django.po
formtools/locale/be/LC_MESSAGES/django.mo
formtools/locale/be/LC_MESSAGES/django.po
formtools/locale/bg/LC_MESSAGES/django.mo
formtools/locale/bg/LC_MESSAGES/django.po
formtools/locale/br/LC_MESSAGES/django.mo
formtools/locale/br/LC_MESSAGES/django.po
formtools/locale/ca/LC_MESSAGES/django.mo
formtools/locale/ca/LC_MESSAGES/django.po
formtools/locale/cs/LC_MESSAGES/django.mo
formtools/locale/cs/LC_MESSAGES/django.po
formtools/locale/cy/LC_MESSAGES/django.mo
formtools/locale/cy/LC_MESSAGES/django.po
formtools/locale/da/LC_MESSAGES/django.mo
formtools/locale/da/LC_MESSAGES/django.po
formtools/locale/de/LC_MESSAGES/django.mo
formtools/locale/de/LC_MESSAGES/django.po
formtools/locale/el/LC_MESSAGES/django.mo
formtools/locale/el/LC_MESSAGES/django.po
formtools/locale/en/LC_MESSAGES/django.mo
formtools/locale/en/LC_MESSAGES/django.po
formtools/locale/en_GB/LC_MESSAGES/django.mo
formtools/locale/en_GB/LC_MESSAGES/django.po
formtools/locale/eo/LC_MESSAGES/django.mo
formtools/locale/eo/LC_MESSAGES/django.po
formtools/locale/es/LC_MESSAGES/django.mo
formtools/locale/es/LC_MESSAGES/django.po
formtools/locale/es_AR/LC_MESSAGES/django.mo
formtools/locale/es_AR/LC_MESSAGES/django.po
formtools/locale/es_MX/LC_MESSAGES/django.mo
formtools/locale/es_MX/LC_MESSAGES/django.po
formtools/locale/et/LC_MESSAGES/django.mo
formtools/locale/et/LC_MESSAGES/django.po
formtools/locale/eu/LC_MESSAGES/django.mo
formtools/locale/eu/LC_MESSAGES/django.po
formtools/locale/fa/LC_MESSAGES/django.mo
formtools/locale/fa/LC_MESSAGES/django.po
django_formtools-2.5.1.dist-info/LICENSE
django_formtools-2.5.1.dist-info/METADATA
django_formtools-2.5.1.dist-info/WHEEL
django_formtools-2.5.1.dist-info/top_level.txt
django_formtools-2.5.1.dist-info/RECORD
